zzdb/UNKNOWN.egg-info/PKG-INFO
zzdb/UNKNOWN.egg-info/SOURCES.txt
zzdb/UNKNOWN.egg-info/dependency_links.txt
zzdb/UNKNOWN.egg-info/top_level.txt
zzdb/__init__.py
zzdb/cursor.py
zzdb/db.py
zzdb/schema.py
zzdb/utils.py
zzdb-0.1.11.dist-info/LICENSE
zzdb-0.1.11.dist-info/WHEEL
zzdb-0.1.11.dist-info/METADATA
zzdb-0.1.11.dist-info/RECORD
