Metadata-Version: 2.1
Name: zzdb
Version: 0.1.11
Summary: python DB API wrapper (MySQL, PostgreSQL, SQLite)
License: Apache 2.0
Author: Andrei Puchko
Author-email: andrei.puchko@gmx.de
Requires-Python: >=3.7,<4.0
Classifier: License :: Other/Proprietary License
Classifier: Programming Language :: Python :: 3
Classifier: Programming Language :: Python :: 3.10
Classifier: Programming Language :: Python :: 3.7
Classifier: Programming Language :: Python :: 3.8
Classifier: Programming Language :: Python :: 3.9
